structuralcodes/__init__.py
structuralcodes/codes/__init__.py
structuralcodes/codes/ec2_2004/__init__.py
structuralcodes/codes/ec2_2004/_concrete_creep_and_shrinkage.py
structuralcodes/codes/ec2_2004/_concrete_material_properties.py
structuralcodes/codes/ec2_2004/_cracking_restraint_imposed_deformations.py
structuralcodes/codes/ec2_2004/_reinforcement_material_properties.py
structuralcodes/codes/ec2_2004/_section_7_3_crack_control.py
structuralcodes/codes/ec2_2004/shear.py
structuralcodes/codes/ec2_2023/__init__.py
structuralcodes/codes/ec2_2023/_annexB_time_dependent.py
structuralcodes/codes/ec2_2023/_section5_materials.py
structuralcodes/codes/ec2_2023/_section9_sls.py
structuralcodes/codes/mc2010/__init__.py
structuralcodes/codes/mc2010/_concrete_creep_and_shrinkage.py
structuralcodes/codes/mc2010/_concrete_interface_different_casting_times.py
structuralcodes/codes/mc2010/_concrete_material_properties.py
structuralcodes/codes/mc2010/_concrete_punching.py
structuralcodes/codes/mc2010/_concrete_shear.py
structuralcodes/codes/mc2010/_concrete_torsion.py
structuralcodes/codes/mc2010/_interface_concrete_steel_rebar.py
structuralcodes/codes/mc2010/_reinforcement_material_properties.py
structuralcodes/codes/mc2020/__init__.py
structuralcodes/core/__init__.py
structuralcodes/core/_marin_integration.py
structuralcodes/core/_section_results.py
structuralcodes/core/base.py
structuralcodes/geometry/__init__.py
structuralcodes/geometry/_circular.py
structuralcodes/geometry/_geometry.py
structuralcodes/geometry/_rectangular.py
structuralcodes/geometry/_reinforcement.py
structuralcodes/geometry/profiles/__init__.py
structuralcodes/geometry/profiles/_base_profile.py
structuralcodes/geometry/profiles/_common_functions.py
structuralcodes/geometry/profiles/_hd.py
structuralcodes/geometry/profiles/_he.py
structuralcodes/geometry/profiles/_hp.py
structuralcodes/geometry/profiles/_ipe.py
structuralcodes/geometry/profiles/_ipn.py
structuralcodes/geometry/profiles/_l.py
structuralcodes-0.6.3.dist-info/licenses/LICENSE
structuralcodes-0.6.3.dist-info/WHEEL
structuralcodes-0.6.3.dist-info/METADATA
structuralcodes-0.6.3.dist-info/RECORD
