Metadata-Version: 2.4
Name: structuralcodes
Version: 0.6.3
Summary: A Python package that contains models from structural design codes.
Author-email: fib - International Federation for Structural Concrete <info@fib-international.org>
Requires-Python: >=3.9
Classifier: Programming Language :: Python :: 3
Classifier: Operating System :: OS Independent
License-File: LICENSE
Requires-Dist: numpy>=1.20.0
Requires-Dist: scipy>=1.6.0
Requires-Dist: shapely>=2.0.2
Requires-Dist: triangle>=20230923
Project-URL: source, https://github.com/fib-international/structuralcodes
